cyberlabrat/__init__.py
cyberlabrat/core/Cacheable.py
cyberlabrat/core/Constants.py
cyberlabrat/core/DataSelection.py
cyberlabrat/core/Dataset.py
cyberlabrat/core/Figure.py
cyberlabrat/core/FileSystem.py
cyberlabrat/core/HPLC.py
cyberlabrat/core/JSON.py
cyberlabrat/core/Matrix.py
cyberlabrat/core/Metadata.py
cyberlabrat/core/Project.py
cyberlabrat/core/Statistics.py
cyberlabrat/core/__init__.py
cyberlabrat/core/display.py
cyberlabrat/core/questions.py
cyberlabrat/core/utils.py
cyberlabrat/json/__init__.py
cyberlabrat/json/circuits.json
cyberlabrat/json/compound_classes.json
cyberlabrat/json/compounds.json
cyberlabrat/json/region_classes.json
cyberlabrat/json/regions.json
cyberlabrat/json/regions_idealy.json
cyberlabrat-0.1.10.dist-info/METADATA
cyberlabrat-0.1.10.dist-info/WHEEL
cyberlabrat-0.1.10.dist-info/top_level.txt
cyberlabrat-0.1.10.dist-info/RECORD
