Metadata-Version: 2.1
Name: cyberlabrat
Version: 0.1.10
Summary: Contains the classes used for generix data analysis
Home-page: https://github.com/jjb-hub/phd
Author: Jasmine Butler & Remi Corne
Author-email: remi.corne@gmail.com
Classifier: Programming Language :: Python :: 3
Classifier: License :: OSI Approved :: MIT License
Classifier: Operating System :: OS Independent
Requires-Python: >=3.10
Requires-Dist: pandas==2.0.3
Requires-Dist: matplotlib==3.7.3
Requires-Dist: outlier-utils
Requires-Dist: pingouin
Requires-Dist: scipy
Requires-Dist: remi-statannotations-fork
Requires-Dist: setuptools
Requires-Dist: statsmodels
Requires-Dist: openpyxl
Requires-Dist: pydantic
Requires-Dist: pytest
Requires-Dist: tqdm
Requires-Dist: ipykernel
Requires-Dist: ipywidgets
Requires-Dist: IPython
Requires-Dist: networkx
